[
  {
    "org": "FRC 604: Quixilver Robotics",
    "position": "Controls/Software Lead (10-11)",
    "startYear": "2022",
    "endYear": "2024",
    "ongoing": true,
    "details": [
      {
        "point": "Develop team's competition data collection application, enhance robot capabilities and localization with computer vision and environmental sensors, contribute to team software (particle filter, time-optimal trajectory optimizer, yearly robot control architecture)."
      },
      {
        "point": "Lead subteams in design, manufacturing, and programming of team robot while training new members to contribute to robot development. Attend/host 20+ STEM community outreach events."
      },
      {
        "point": "Contribute to progressive web app and add data to universal FRC competition data aggregation and real time insight platform TheBlueAlliance."
      }
    ],
    "icon": {
      "src": "/static/icons/frc604.jpeg",
      "link": "https://604robotics.com/"
    },
    "hideOnSite": false,
    "hideOnResume": false
  },
  {
    "org": "UCLA COSMOS (CA Summer School for Mathematics & Science)",
    "position": "Brain-Inspired Computing Cohort Member",
    "startYear": "2024",
    "endYear": "2024",
    "ongoing": false,
    "details": [
      {
        "point": "Investigated machine learning advancements (attention, visual processing, recurrent systems, reinforcement, etc) alongside their neurological foundations."
      },
      {
        "point": "Developed novel audio generation ML framework with UC funding."
      }
    ],
    "icon": {
      "src": "/static/icons/cosmos.jpg",
      "link": "https://cosmos.ucla.edu/"
    },
    "hideOnSite": false,
    "hideOnResume": false
  },
  {
    "org": "Bay Area STEM Academy",
    "position": "Cofounder",
    "startYear": "2023",
    "endYear": "2024",
    "ongoing": true,
    "details": [
      {
        "point": "Developed engaging curricula, recruited mentors, planned and effectively in-person and online camps encompassing diverse STEM fields."
      },
      {
        "point": "Impacted 700+ students and raised $6000+ to support organization costs, local STEM outreach initiatives for underrepresented communities, and children health foundations."
      }
    ],
    "icon": {
      "src": "/static/icons/basa.jpeg",
      "link": "https://bayareastemacademy.net/"
    },
    "hideOnSite": false,
    "hideOnResume": false
  },
  {
    "org": "Leland Speech and Debate (NSDA)",
    "position": "Varsity Speaker",
    "startYear": "2022",
    "endYear": "2024",
    "ongoing": true,
    "details": [
      {
        "point": "Refine argumentation skills and rapidly synthesize speeches to compete on an international level."
      },
      {
        "point": "Competed in 20+ tournaments as member of 3/3550+ ranked NSDA program."
      }
    ],
    "icon": {
      "src": "/static/icons/lsd.jpg",
      "link": "https://www.lelandsd.org/"
    },
    "hideOnSite": true,
    "hideOnResume": true
  }
]
